a_share_mcp/__init__.py
a_share_mcp/baostock_data_source.py
a_share_mcp/data_source_interface.py
a_share_mcp/mcp_server.py
a_share_mcp/utils.py
a_share_mcp/formatting/__init__.py
a_share_mcp/formatting/markdown_formatter.py
a_share_mcp/tools/__init__.py
a_share_mcp/tools/analysis.py
a_share_mcp/tools/base.py
a_share_mcp/tools/date_utils.py
a_share_mcp/tools/financial_reports.py
a_share_mcp/tools/indices.py
a_share_mcp/tools/macroeconomic.py
a_share_mcp/tools/market_overview.py
a_share_mcp/tools/stock_market.py
ashare_mcp-0.3.1.dist-info/METADATA
ashare_mcp-0.3.1.dist-info/WHEEL
ashare_mcp-0.3.1.dist-info/entry_points.txt
ashare_mcp-0.3.1.dist-info/top_level.txt
ashare_mcp-0.3.1.dist-info/RECORD
